{
    "30976355-bb44-31eb-6bcd-4fad657f09a2": {
        "paletteKey": "FlexLayoutRow",
        "designerReference": [
            {
                "_key": "componentLabel",
                "_value": "Row",
                "_type": "kv",
                "_attrDef": "p",
                "_useAsLabel": true
            },
            {
                "_key": "style",
                "_value": "width:100%;  ",
                "_type": "kv",
                "_attrDef": "p"
            },
            {
                "_key": "class",
                "_value": "",
                "_type": "kv",
                "_attrDef": "p"
            },
            {
                "_key": "fxFlex",
                "_value": "",
                "_type": "kv",
                "_attrDef": "p"
            },
            {
                "_key": "fxLayoutGap",
                "_value": "",
                "_type": "kv",
                "_attrDef": "p"
            },
            {
                "_key": "wrap",
                "_value": "wrap",
                "_type": "a",
                "_attrDef": "p"
            },
            {
                "_key": "layoutAlign",
                "_value": "start",
                "_type": "a",
                "_attrDef": "p"
            },
            {
                "_key": "pLayoutAlign",
                "_value": "stretch",
                "_type": "a",
                "_attrDef": "p"
            },
            {
                "_key": "fxShow",
                "_value": "true",
                "_type": "kv",
                "_attrDef": "p"
            },
            {
                "_key": "fxHide",
                "_value": "false",
                "_type": "kv",
                "_attrDef": "p"
            }
        ],
        "282150d4-e0f7-ef91-a77e-5fe86d457a6a": {
            "paletteKey": "FlexLayoutCol",
            "parentEditorKey": "30976355-bb44-31eb-6bcd-4fad657f09a2",
            "designerReference": [
                {
                    "_key": "componentLabel",
                    "_value": "Column",
                    "_type": "kv",
                    "_attrDef": "p",
                    "_useAsLabel": true
                },
                {
                    "_key": "style",
                    "_value": "height: 100%;",
                    "_type": "kv",
                    "_attrDef": "p"
                },
                {
                    "_key": "class",
                    "_value": "container",
                    "_type": "kv",
                    "_attrDef": "p"
                },
                {
                    "_key": "fxFlex",
                    "_value": "100",
                    "_type": "kv",
                    "_attrDef": "p"
                },
                {
                    "_key": "fxLayoutGap",
                    "_value": "",
                    "_type": "kv",
                    "_attrDef": "p"
                },
                {
                    "_key": "wrap",
                    "_value": "wrap",
                    "_type": "a",
                    "_attrDef": "p"
                },
                {
                    "_key": "layoutAlign",
                    "_value": "start",
                    "_type": "a",
                    "_attrDef": "p"
                },
                {
                    "_key": "pLayoutAlign",
                    "_value": "stretch",
                    "_type": "a",
                    "_attrDef": "p"
                },
                {
                    "_key": "fxShow",
                    "_value": "true",
                    "_type": "kv",
                    "_attrDef": "p"
                },
                {
                    "_key": "fxHide",
                    "_value": "false",
                    "_type": "kv",
                    "_attrDef": "p"
                },
                {
                    "_key": "ngClass.sm",
                    "_value": "containerTablet",
                    "_type": "kv",
                    "_attrDef": "c"
                }
            ],
            "03205d6b-56bf-d7de-0d84-1f572cc06eb7": {
                "paletteKey": "FlexLayoutCol",
                "parentEditorKey": "282150d4-e0f7-ef91-a77e-5fe86d457a6a",
                "designerReference": [
                    {
                        "_key": "componentLabel",
                        "_value": "Column",
                        "_type": "kv",
                        "_attrDef": "p",
                        "_useAsLabel": true
                    },
                    {
                        "_key": "style",
                        "_value": "padding-top: 10px;",
                        "_type": "kv",
                        "_attrDef": "p"
                    },
                    {
                        "_key": "class",
                        "_value": "",
                        "_type": "kv",
                        "_attrDef": "p"
                    },
                    {
                        "_key": "fxFlex",
                        "_value": "",
                        "_type": "kv",
                        "_attrDef": "p"
                    },
                    {
                        "_key": "fxLayoutGap",
                        "_value": "",
                        "_type": "kv",
                        "_attrDef": "p"
                    },
                    {
                        "_key": "wrap",
                        "_value": "wrap",
                        "_type": "a",
                        "_attrDef": "p"
                    },
                    {
                        "_key": "layoutAlign",
                        "_value": "start",
                        "_type": "a",
                        "_attrDef": "p"
                    },
                    {
                        "_key": "pLayoutAlign",
                        "_value": "stretch",
                        "_type": "a",
                        "_attrDef": "p"
                    },
                    {
                        "_key": "fxShow",
                        "_value": "true",
                        "_type": "kv",
                        "_attrDef": "p"
                    },
                    {
                        "_key": "fxHide",
                        "_value": "false",
                        "_type": "kv",
                        "_attrDef": "p"
                    }
                ],
                "1285a2bf-7505-8d00-29b2-dabe9d261c17": {
                    "paletteKey": "FlexLayoutRow",
                    "parentEditorKey": "03205d6b-56bf-d7de-0d84-1f572cc06eb7",
                    "designerReference": [
                        {
                            "_key": "componentLabel",
                            "_value": "Header - navbar",
                            "_type": "kv",
                            "_attrDef": "p",
                            "_useAsLabel": true
                        },
                        {
                            "_key": "style",
                            "_value": "",
                            "_type": "kv",
                            "_attrDef": "p"
                        },
                        {
                            "_key": "class",
                            "_value": "header",
                            "_type": "kv",
                            "_attrDef": "p"
                        },
                        {
                            "_key": "fxFlex",
                            "_value": "100",
                            "_type": "kv",
                            "_attrDef": "p"
                        },
                        {
                            "_key": "fxLayoutGap",
                            "_value": "",
                            "_type": "kv",
                            "_attrDef": "p"
                        },
                        {
                            "_key": "wrap",
                            "_value": "wrap",
                            "_type": "a",
                            "_attrDef": "p"
                        },
                        {
                            "_key": "layoutAlign",
                            "_value": "center",
                            "_type": "a",
                            "_attrDef": "p"
                        },
                        {
                            "_key": "pLayoutAlign",
                            "_value": "stretch",
                            "_type": "a",
                            "_attrDef": "p"
                        },
                        {
                            "_key": "fxShow",
                            "_value": "true",
                            "_type": "kv",
                            "_attrDef": "p"
                        },
                        {
                            "_key": "fxHide",
                            "_value": "false",
                            "_type": "kv",
                            "_attrDef": "p"
                        }
                    ],
                    "727a2381-24c6-9fe4-87f9-0e4b28d16263": {
                        "paletteKey": "FlexLayoutCol",
                        "parentEditorKey": "1285a2bf-7505-8d00-29b2-dabe9d261c17",
                        "designerReference": [
                            {
                                "_key": "componentLabel",
                                "_value": "Column",
                                "_type": "kv",
                                "_attrDef": "p",
                                "_useAsLabel": true
                            },
                            {
                                "_key": "style",
                                "_value": "",
                                "_type": "kv",
                                "_attrDef": "p"
                            },
                            {
                                "_key": "class",
                                "_value": "logo",
                                "_type": "kv",
                                "_attrDef": "p"
                            },
                            {
                                "_key": "fxFlex",
                                "_value": "50",
                                "_type": "kv",
                                "_attrDef": "p"
                            },
                            {
                                "_key": "fxLayoutGap",
                                "_value": "",
                                "_type": "kv",
                                "_attrDef": "p"
                            },
                            {
                                "_key": "wrap",
                                "_value": "wrap",
                                "_type": "a",
                                "_attrDef": "p"
                            },
                            {
                                "_key": "layoutAlign",
                                "_value": "center",
                                "_type": "a",
                                "_attrDef": "p"
                            },
                            {
                                "_key": "pLayoutAlign",
                                "_value": "stretch",
                                "_type": "a",
                                "_attrDef": "p"
                            },
                            {
                                "_key": "fxShow",
                                "_value": "true",
                                "_type": "kv",
                                "_attrDef": "p"
                            },
                            {
                                "_key": "fxHide",
                                "_value": "false",
                                "_type": "kv",
                                "_attrDef": "p"
                            },
                            {
                                "_key": "fxFlex.xs",
                                "_value": "30",
                                "_type": "kv",
                                "_attrDef": "c"
                            }
                        ],
                        "3e86a8db-5959-52af-9787-cbfe86e718aa": {
                            "paletteKey": "NG-image",
                            "parentEditorKey": "727a2381-24c6-9fe4-87f9-0e4b28d16263",
                            "designerReference": [
                                {
                                    "_key": "componentLabel",
                                    "_value": "Image",
                                    "_type": "kv",
                                    "_attrDef": "p",
                                    "_useAsLabel": true
                                },
                                {
                                    "_key": "style",
                                    "_value": "cursor:pointer",
                                    "_type": "kv",
                                    "_attrDef": "p"
                                },
                                {
                                    "_key": "class",
                                    "_value": "",
                                    "_type": "kv",
                                    "_attrDef": "p"
                                },
                                {
                                    "_key": "imgSrc",
                                    "_value": "/Web/new-logo.png",
                                    "_type": "kv",
                                    "_attrDef": "p"
                                },
                                {
                                    "_key": "alt",
                                    "_value": "",
                                    "_type": "kv",
                                    "_attrDef": "p"
                                },
                                {
                                    "_key": "[src]",
                                    "_value": "",
                                    "_type": "kv",
                                    "_attrDef": "p"
                                },
                                {
                                    "_key": "imgSecure",
                                    "_value": "",
                                    "_type": "a",
                                    "_attrDef": "p"
                                },
                                {
                                    "_key": "[collectionName]",
                                    "_value": "",
                                    "_type": "kv",
                                    "_attrDef": "p"
                                },
                                {
                                    "_key": "[imageFilter]",
                                    "_value": "",
                                    "_type": "kv",
                                    "_attrDef": "p"
                                },
                                {
                                    "_key": "width",
                                    "_value": "",
                                    "_type": "kv",
                                    "_attrDef": "p"
                                },
                                {
                                    "_key": "srcset",
                                    "_value": "",
                                    "_type": "kv",
                                    "_attrDef": "p"
                                },
                                {
                                    "_key": "sizes",
                                    "_value": "",
                                    "_type": "kv",
                                    "_attrDef": "p"
                                },
                                {
                                    "_key": "routerLink",
                                    "_value": "/home",
                                    "_type": "kv",
                                    "_attrDef": "c"
                                }
                            ]
                        }
                    },
                    "69d5aa2a-20c0-a891-59e2-8cb4aee9e1a1": {
                        "paletteKey": "FlexLayoutCol",
                        "parentEditorKey": "1285a2bf-7505-8d00-29b2-dabe9d261c17",
                        "designerReference": [
                            {
                                "_key": "componentLabel",
                                "_value": "Column",
                                "_type": "kv",
                                "_attrDef": "p",
                                "_useAsLabel": true
                            },
                            {
                                "_key": "style",
                                "_value": "",
                                "_type": "kv",
                                "_attrDef": "p"
                            },
                            {
                                "_key": "class",
                                "_value": "menu",
                                "_type": "kv",
                                "_attrDef": "p"
                            },
                            {
                                "_key": "fxFlex",
                                "_value": "50",
                                "_type": "kv",
                                "_attrDef": "p"
                            },
                            {
                                "_key": "fxLayoutGap",
                                "_value": "",
                                "_type": "kv",
                                "_attrDef": "p"
                            },
                            {
                                "_key": "wrap",
                                "_value": "wrap",
                                "_type": "a",
                                "_attrDef": "p"
                            },
                            {
                                "_key": "layoutAlign",
                                "_value": "center",
                                "_type": "a",
                                "_attrDef": "p"
                            },
                            {
                                "_key": "pLayoutAlign",
                                "_value": "end",
                                "_type": "a",
                                "_attrDef": "p"
                            },
                            {
                                "_key": "fxShow",
                                "_value": "true",
                                "_type": "kv",
                                "_attrDef": "p"
                            },
                            {
                                "_key": "fxHide",
                                "_value": "false",
                                "_type": "kv",
                                "_attrDef": "p"
                            },
                            {
                                "_key": "fxFlex.xs",
                                "_value": "60",
                                "_type": "kv",
                                "_attrDef": "c"
                            }
                        ],
                        "34963927-2326-2af2-be0c-8c1c16ec3f4b": {
                            "paletteKey": "FlexLayoutRow",
                            "parentEditorKey": "69d5aa2a-20c0-a891-59e2-8cb4aee9e1a1",
                            "designerReference": [
                                {
                                    "_key": "componentLabel",
                                    "_value": "Row",
                                    "_type": "kv",
                                    "_attrDef": "p",
                                    "_useAsLabel": true
                                },
                                {
                                    "_key": "style",
                                    "_value": "",
                                    "_type": "kv",
                                    "_attrDef": "p"
                                },
                                {
                                    "_key": "class",
                                    "_value": "",
                                    "_type": "kv",
                                    "_attrDef": "p"
                                },
                                {
                                    "_key": "fxFlex",
                                    "_value": "",
                                    "_type": "kv",
                                    "_attrDef": "p"
                                },
                                {
                                    "_key": "fxLayoutGap",
                                    "_value": "",
                                    "_type": "kv",
                                    "_attrDef": "p"
                                },
                                {
                                    "_key": "wrap",
                                    "_value": "wrap",
                                    "_type": "a",
                                    "_attrDef": "p"
                                },
                                {
                                    "_key": "layoutAlign",
                                    "_value": "center",
                                    "_type": "a",
                                    "_attrDef": "p"
                                },
                                {
                                    "_key": "pLayoutAlign",
                                    "_value": "center",
                                    "_type": "a",
                                    "_attrDef": "p"
                                },
                                {
                                    "_key": "fxShow",
                                    "_value": "true",
                                    "_type": "kv",
                                    "_attrDef": "p"
                                },
                                {
                                    "_key": "fxHide",
                                    "_value": "false",
                                    "_type": "kv",
                                    "_attrDef": "p"
                                }
                            ],
                            "d310f3f8-b761-3ecc-a10d-62cd8d63b3d2": {
                                "paletteKey": "NG-button",
                                "parentEditorKey": "34963927-2326-2af2-be0c-8c1c16ec3f4b",
                                "designerReference": [
                                    {
                                        "_key": "style",
                                        "_value": "",
                                        "_type": "kv",
                                        "_attrDef": "p"
                                    },
                                    {
                                        "_key": "class",
                                        "_value": "",
                                        "_type": "kv",
                                        "_attrDef": "p"
                                    },
                                    {
                                        "_key": "buttonname",
                                        "_value": "Criteria",
                                        "_type": "a",
                                        "_attrDef": "p",
                                        "_useAsLabel": true
                                    },
                                    {
                                        "_key": "color",
                                        "_value": "",
                                        "_type": "kv",
                                        "_attrDef": "p"
                                    },
                                    {
                                        "_key": "(click)",
                                        "_value": "",
                                        "_type": "kv",
                                        "_attrDef": "p"
                                    },
                                    {
                                        "_key": "[disabled]",
                                        "_value": "",
                                        "_type": "kv",
                                        "_attrDef": "p"
                                    },
                                    {
                                        "_key": "[disableRipple]",
                                        "_value": "",
                                        "_type": "kv",
                                        "_attrDef": "p"
                                    },
                                    {
                                        "_key": "type",
                                        "_value": "",
                                        "_type": "kv",
                                        "_attrDef": "p"
                                    },
                                    {
                                        "_key": "routerLink",
                                        "_value": "criteria",
                                        "_type": "kv",
                                        "_attrDef": "p"
                                    }
                                ]
                            },
                            "4b477da1-8c4b-47cb-d6a2-2e3517c8f353": {
                                "paletteKey": "NG-button",
                                "parentEditorKey": "34963927-2326-2af2-be0c-8c1c16ec3f4b",
                                "designerReference": [
                                    {
                                        "_key": "style",
                                        "_value": "",
                                        "_type": "kv",
                                        "_attrDef": "p"
                                    },
                                    {
                                        "_key": "class",
                                        "_value": "",
                                        "_type": "kv",
                                        "_attrDef": "p"
                                    },
                                    {
                                        "_key": "buttonname",
                                        "_value": "Register",
                                        "_type": "a",
                                        "_attrDef": "p",
                                        "_useAsLabel": true
                                    },
                                    {
                                        "_key": "color",
                                        "_value": "",
                                        "_type": "kv",
                                        "_attrDef": "p"
                                    },
                                    {
                                        "_key": "(click)",
                                        "_value": "",
                                        "_type": "kv",
                                        "_attrDef": "p"
                                    },
                                    {
                                        "_key": "[disabled]",
                                        "_value": "",
                                        "_type": "kv",
                                        "_attrDef": "p"
                                    },
                                    {
                                        "_key": "[disableRipple]",
                                        "_value": "",
                                        "_type": "kv",
                                        "_attrDef": "p"
                                    },
                                    {
                                        "_key": "type",
                                        "_value": "",
                                        "_type": "kv",
                                        "_attrDef": "p"
                                    },
                                    {
                                        "_key": "routerLink",
                                        "_value": "register",
                                        "_type": "kv",
                                        "_attrDef": "p"
                                    }
                                ]
                            }
                        }
                    }
                }
            },
            "e4a63d9c-8630-c965-65ad-707722f9205a": {
                "paletteKey": "FlexLayoutCol",
                "parentEditorKey": "282150d4-e0f7-ef91-a77e-5fe86d457a6a",
                "designerReference": [
                    {
                        "_key": "componentLabel",
                        "_value": "Column",
                        "_type": "kv",
                        "_attrDef": "p",
                        "_useAsLabel": true
                    },
                    {
                        "_key": "style",
                        "_value": "",
                        "_type": "kv",
                        "_attrDef": "p"
                    },
                    {
                        "_key": "class",
                        "_value": "",
                        "_type": "kv",
                        "_attrDef": "p"
                    },
                    {
                        "_key": "fxFlex",
                        "_value": "",
                        "_type": "kv",
                        "_attrDef": "p"
                    },
                    {
                        "_key": "fxLayoutGap",
                        "_value": "",
                        "_type": "kv",
                        "_attrDef": "p"
                    },
                    {
                        "_key": "wrap",
                        "_value": "wrap",
                        "_type": "a",
                        "_attrDef": "p"
                    },
                    {
                        "_key": "layoutAlign",
                        "_value": "start",
                        "_type": "a",
                        "_attrDef": "p"
                    },
                    {
                        "_key": "pLayoutAlign",
                        "_value": "stretch",
                        "_type": "a",
                        "_attrDef": "p"
                    },
                    {
                        "_key": "fxShow",
                        "_value": "true",
                        "_type": "kv",
                        "_attrDef": "p"
                    },
                    {
                        "_key": "fxHide",
                        "_value": "false",
                        "_type": "kv",
                        "_attrDef": "p"
                    },
                    {
                        "_key": "fxFill",
                        "_value": "fxFill",
                        "_type": "a",
                        "_attrDef": "c"
                    }
                ],
                "cfc211ec-d196-e06a-f1a4-b6686b1f6651": {
                    "paletteKey": "NG-RouterOutlet",
                    "parentEditorKey": "e4a63d9c-8630-c965-65ad-707722f9205a",
                    "designerReference": [
                        {
                            "_key": "componentLabel",
                            "_value": "Router Outlet",
                            "_type": "kv",
                            "_attrDef": "p",
                            "_useAsLabel": true
                        },
                        {
                            "_key": "style",
                            "_value": "",
                            "_type": "kv",
                            "_attrDef": "p"
                        },
                        {
                            "_key": "class",
                            "_value": "",
                            "_type": "kv",
                            "_attrDef": "p"
                        },
                        {
                            "_key": "(activate)",
                            "_value": "",
                            "_type": "kv",
                            "_attrDef": "p"
                        },
                        {
                            "_key": "(deactivate)",
                            "_value": "",
                            "_type": "kv",
                            "_attrDef": "p"
                        },
                        {
                            "_key": "isActivated",
                            "_value": "",
                            "_type": "kv",
                            "_attrDef": "p"
                        }
                    ]
                }
            }
        }
    }
}
